{
  "endpoints": {
    "serverUrl": "https://test.thaproban.sewapiyasa.com/api/v1",
    "brands": {
      "fetchAll": "brands?perPage={pageSize}&page={pageNo}&searchText={searchTerm}",
      "fetchById": "brands/{id}",
      "create": "brands",
      "update": "brands/{id}",
      "delete": "brands/{id}",
      "checkDeletable": "brands/{id}/check-deletable"
    },
    "categories": {
      "fetchAll": "categories?perPage={pageSize}&page={pageNo}&searchText={searchTerm}",
      "fetchById": "categories/{id}",
      "create": "categories",
      "update": "categories/{id}",
      "delete": "categories/{id}",
      "checkDeletable": "categories/{id}/check-deletable"
    },
    "banks": {
      "fetchAll": "banks?perPage={pageSize}&page={pageNo}&searchText={searchTerm}",
      "fetchById": "banks/{id}",
      "create": "banks",
      "update": "banks/{id}",
      "delete": "banks/{id}",
      "checkDeletable": "banks/{id}/check-deletable"
    }
  }
}